SHU_cxAutoSign/__init__.py
SHU_cxAutoSign/login.py
SHU_cxAutoSign-0.2.0.dist-info/LICENSE
SHU_cxAutoSign-0.2.0.dist-info/METADATA
SHU_cxAutoSign-0.2.0.dist-info/WHEEL
SHU_cxAutoSign-0.2.0.dist-info/top_level.txt
SHU_cxAutoSign-0.2.0.dist-info/RECORD
