Metadata-Version: 2.1
Name: SHU-cxAutoSign
Version: 0.2.0
Summary: UNKNOWN
Home-page: https://github.com/pypa/sampleproject
Author: XHLin
Author-email: xhaughearl@gmail.com
License: UNKNOWN
Project-URL: Bug Tracker, https://github.com/pypa/sampleproject/issues
Platform: UNKNOWN
Classifier: Programming Language :: Python :: 3
Classifier: License :: OSI Approved :: MIT License
Classifier: Operating System :: OS Independent
Requires-Python: >=3.6
License-File: LICENSE
Requires-Dist: ras
Requires-Dist: lxml
Requires-Dist: requests
Requires-Dist: beautifulsoup4
